src/__init__.py
src/approvalWebAppBackendApiConnector.py
tim_approval-0.0.2.dist-info/METADATA
tim_approval-0.0.2.dist-info/WHEEL
tim_approval-0.0.2.dist-info/licenses/license.txt
tim_approval-0.0.2.dist-info/RECORD
